mec/__init__.py
mec/blp.py
mec/data.py
mec/gt.py
mec/lp.py
mec/mx.py
mec/nf.py
mec/nf_newest.py
mec/ot.py
mec/ph.py
mec/test.py
mec/utils.py
mec/datasets/StiglerData1939.txt
mec/datasets/__init__.py
mec/datasets/demand_blp/readme.txt
mec/datasets/demand_blp/blp_1999/lagged_erate.asc
mec/datasets/demand_blp/blp_1999/otherdat.asc
mec/datasets/demand_blp/blp_1999/otherdat3.asc
mec/datasets/demand_blp/blp_1999/panel6.asc
mec/datasets/demand_blp/blp_1999/readme.txt
mec/datasets/demand_blp/gentzkow-shapiro/unobs_pub.csv
mec/datasets/demand_blp/preloaded/agents.csv
mec/datasets/demand_blp/preloaded/prod.csv
mec/datasets/demand_travelmode/readme.txt
mec/datasets/demand_travelmode/travelmodedata.csv
mec/datasets/dynamicchoice_Rust/a452372.asc
mec/datasets/dynamicchoice_Rust/a452374.asc
mec/datasets/dynamicchoice_Rust/a530872.asc
mec/datasets/dynamicchoice_Rust/a530874.asc
mec/datasets/dynamicchoice_Rust/a530875.asc
mec/datasets/dynamicchoice_Rust/d309.asc
mec/datasets/dynamicchoice_Rust/g870.asc
mec/datasets/dynamicchoice_Rust/readme.txt
mec/datasets/dynamicchoice_Rust/rt50.asc
mec/datasets/dynamicchoice_Rust/t8h203.asc
mec/datasets/gravity_wtodata/1_TraditionalGravity_from_WTO_book.csv
mec/datasets/marriage-ChooSiow/marr.txt
mec/datasets/marriage-ChooSiow/n_avail.txt
mec/datasets/marriage-ChooSiow/n_singles.txt
mec/datasets/marriage_fatterattraction/female.csv
mec/datasets/marriage_fatterattraction/male.csv
mec/datasets/marriage_personality-traits/Xvals.csv
mec/datasets/marriage_personality-traits/Yvals.csv
mec/datasets/marriage_personality-traits/affinitymatrix.csv
mec/datasets/networks_sovietplanning/distances.csv
mec/datasets/networks_sovietplanning/readme.txt
mec/datasets/networks_subway/NYC/arcs.csv
mec/datasets/networks_subway/NYC/nodes.csv
mec/datasets/networks_subway/NYC/readme.txt
mec/datasets/networks_subway/Paris/arcs.csv
mec/datasets/networks_subway/Paris/nodes.csv
mec/datasets/networks_subway/Paris/readme.txt
mec/datasets/stigler-diet/StiglerData1939.txt
mec-0.227.dist-info/METADATA
mec-0.227.dist-info/WHEEL
mec-0.227.dist-info/top_level.txt
mec-0.227.dist-info/RECORD
