Metadata-Version: 2.4
Name: mec
Version: 0.227
Summary: description of the package
Author-email: Alfred Galichon <ag133@nyu.edu>
Requires-Python: >=3
Requires-Dist: gurobipy
Requires-Dist: PyGithub
Requires-Dist: python-dotenv
